[
    {
      "_id": "1",
      "name": "Tutorial-Trail",
      "video": "https://www.youtube.com/watch?v=I7YX1cqvIwI&list=PLfDmeEHel1x3o_e4UjWXR4kClH7ZfAgZ9"
    },
    {
      "_id": "2",
      "name": "Tutorial-1",
      "video": "https://www.youtube.com/watch?v=91lIllsNR6c&list=PLfDmeEHel1x3o_e4UjWXR4kClH7ZfAgZ9&index=2"
    },
    {
      "_id": "3",
      "name": "Tutorial-2",
      "video": "https://www.youtube.com/watch?v=zUqN88nTX4Y&list=PLfDmeEHel1x3o_e4UjWXR4kClH7ZfAgZ9&index=3"
    },
    {
      "_id": "4",
      "name": "Tutorial-3",
      "video": "https://www.youtube.com/watch?v=axBmhDmynxQ&list=PLpuxPG4TUOR5-DVxgV3EzxtecZVjmkPp9&index=4"
    },
    {
      "_id": "5",
      "name": "Tutorial-4",
      "video": "https://www.youtube.com/watch?v=jj547fcqN4k&list=PLfDmeEHel1x3o_e4UjWXR4kClH7ZfAgZ9&index=5"
    },
    {
      "_id": "6",
      "name": "Tutorial-5",
      "video": "https://www.youtube.com/watch?v=xAuq7KNOsVE&list=PLfDmeEHel1x3o_e4UjWXR4kClH7ZfAgZ9&index=6"
    },
    {
      "_id": "7",
      "name": "Tutorial-6",
      "video": "https://www.youtube.com/watch?v=hHLVqu6Dfck&list=PLpuxPG4TUOR5-DVxgV3EzxtecZVjmkPp9&index=7"
    },
    {
      "_id": "8",
      "name": "Tutorial-7",
      "video": "https://www.youtube.com/watch?v=8qCsfEvZz2Q&list=PLfDmeEHel1x3o_e4UjWXR4kClH7ZfAgZ9&index=7"
    },
    {
      "_id": "9",
      "name": "Tutorial-8",
      "video": "https://www.youtube.com/watch?v=n4QrwaQhHLs&list=PLfDmeEHel1x3o_e4UjWXR4kClH7ZfAgZ9&index=8"
    },
    {
      "_id": "10",
      "name": "Tutorial-9",
      "video": "https://www.youtube.com/watch?v=9gtvYUKaXxA&list=PLfDmeEHel1x3o_e4UjWXR4kClH7ZfAgZ9&index=9"
    },
    {
      "_id": "11",
      "name": "Tutorial-10",
      "video": "https://www.youtube.com/watch?v=OSFF9tWVxhA&list=PLfDmeEHel1x3o_e4UjWXR4kClH7ZfAgZ9&index=10"
    }
  ]